aiprint/core.py
aiprint/helper.py
aiprint-0.1.3.dist-info/LICENSE
aiprint-0.1.3.dist-info/METADATA
aiprint-0.1.3.dist-info/WHEEL
aiprint-0.1.3.dist-info/RECORD
